decode_bin-0.1.5.dist-info/METADATA
decode_bin-0.1.5.dist-info/WHEEL
decode_bin/__init__.py
decode_bin/decode_bin.cp38-win_amd64.pyd
decode_bin-0.1.5.dist-info/RECORD
